{
 "cells": [
  {
   "cell_type": "code",
   "execution_count": 13,
   "metadata": {},
   "outputs": [
    {
     "data": {
      "text/plain": [
       "'  1           0 LOAD_CONST               0 (4)\\n              2 LOAD_CONST               1 (54)\\n              4 LOAD_CONST               2 (41)\\n              6 LOAD_CONST               3 (0)\\n              8 LOAD_CONST               4 (112)\\n             10 LOAD_CONST               5 (32)\\n             12 LOAD_CONST               6 (25)\\n             14 LOAD_CONST               7 (49)\\n             16 LOAD_CONST               8 (33)\\n             18 LOAD_CONST               9 (3)\\n             20 LOAD_CONST               3 (0)\\n             22 LOAD_CONST               3 (0)\\n             24 LOAD_CONST              10 (57)\\n             26 LOAD_CONST               5 (32)\\n             28 LOAD_CONST              11 (108)\\n             30 LOAD_CONST              12 (23)\\n             32 LOAD_CONST              13 (48)\\n             34 LOAD_CONST               0 (4)\\n             36 LOAD_CONST              14 (9)\\n             38 LOAD_CONST              15 (70)\\n             40 LOAD_CONST              16 (7)\\n             42 LOAD_CONST              17 (110)\\n             44 LOAD_CONST              18 (36)\\n             46 LOAD_CONST              19 (8)\\n             48 LOAD_CONST              11 (108)\\n             50 LOAD_CONST              16 (7)\\n             52 LOAD_CONST               7 (49)\\n             54 LOAD_CONST              20 (10)\\n             56 LOAD_CONST               0 (4)\\n             58 LOAD_CONST              21 (86)\\n             60 LOAD_CONST              22 (43)\\n             62 LOAD_CONST              11 (108)\\n             64 LOAD_CONST              23 (122)\\n             66 LOAD_CONST              24 (14)\\n             68 LOAD_CONST              25 (2)\\n             70 LOAD_CONST              26 (71)\\n             72 LOAD_CONST              27 (62)\\n             74 LOAD_CONST              28 (115)\\n             76 LOAD_CONST              29 (88)\\n             78 LOAD_CONST              30 (78)\\n             80 BUILD_LIST              40\\n             82 STORE_NAME               0 (input_list)\\n\\n  2          84 LOAD_CONST              31 (\\'J\\')\\n             86 STORE_NAME               1 (key_str)\\n\\n  3          88 LOAD_CONST              32 (\\'_\\')\\n             90 LOAD_NAME                1 (key_str)\\n             92 BINARY_ADD\\n             94 STORE_NAME               1 (key_str)\\n\\n  4          96 LOAD_NAME                1 (key_str)\\n             98 LOAD_CONST              33 (\\'o\\')\\n            100 BINARY_ADD\\n            102 STORE_NAME               1 (key_str)\\n\\n  5         104 LOAD_NAME                1 (key_str)\\n            106 LOAD_CONST              34 (\\'3\\')\\n            108 BINARY_ADD\\n            110 STORE_NAME               1 (key_str)\\n\\n  6         112 LOAD_CONST              35 (\\'t\\')\\n            114 LOAD_NAME                1 (key_str)\\n            116 BINARY_ADD\\n            118 STORE_NAME               1 (key_str)\\n\\n  9         120 LOAD_CONST              36 (<code object <listcomp> at 0x7f5ef6665d40, file \"snake.py\", line 9>)\\n            122 LOAD_CONST              37 (\\'<listcomp>\\')\\n            124 MAKE_FUNCTION            0\\n            126 LOAD_NAME                1 (key_str)\\n            128 GET_ITER\\n            130 CALL_FUNCTION            1\\n            132 STORE_NAME               2 (key_list)\\n\\n 11     >>  134 LOAD_NAME                3 (len)\\n            136 LOAD_NAME                2 (key_list)\\n            138 CALL_FUNCTION            1\\n            140 LOAD_NAME                3 (len)\\n            142 LOAD_NAME                0 (input_list)\\n            144 CALL_FUNCTION            1\\n            146 COMPARE_OP               0 (<)\\n            148 POP_JUMP_IF_FALSE      162\\n\\n 12         150 LOAD_NAME                2 (key_list)\\n            152 LOAD_METHOD              4 (extend)\\n            154 LOAD_NAME                2 (key_list)\\n            156 CALL_METHOD              1\\n            158 POP_TOP\\n            160 JUMP_ABSOLUTE          134\\n\\n 15     >>  162 LOAD_CONST              38 (<code object <listcomp> at 0x7f5ef6665df0, file \"snake.py\", line 15>)\\n            164 LOAD_CONST              37 (\\'<listcomp>\\')\\n            166 MAKE_FUNCTION            0\\n            168 LOAD_NAME                5 (zip)\\n            170 LOAD_NAME                0 (input_list)\\n            172 LOAD_NAME                2 (key_list)\\n            174 CALL_FUNCTION            2\\n            176 GET_ITER\\n            178 CALL_FUNCTION            1\\n            180 STORE_NAME               6 (result)\\n\\n 18         182 LOAD_CONST              39 (\\'\\')\\n            184 LOAD_METHOD              7 (join)\\n            186 LOAD_NAME                8 (map)\\n            188 LOAD_NAME                9 (chr)\\n            190 LOAD_NAME                6 (result)\\n            192 CALL_FUNCTION            2\\n            194 CALL_METHOD              1\\n            196 STORE_NAME              10 (result_text)\\n            198 LOAD_CONST              40 (None)\\n            200 RETURN_VALUE\\n\\nDisassembly of <code object <listcomp> at 0x7f5ef6665d40, file \"snake.py\", line 9>:\\n  9           0 BUILD_LIST               0\\n              2 LOAD_FAST                0 (.0)\\n        >>    4 FOR_ITER                12 (to 18)\\n              6 STORE_FAST               1 (char)\\n              8 LOAD_GLOBAL              0 (ord)\\n             10 LOAD_FAST                1 (char)\\n             12 CALL_FUNCTION            1\\n             14 LIST_APPEND              2\\n             16 JUMP_ABSOLUTE            4\\n        >>   18 RETURN_VALUE\\n\\nDisassembly of <code object <listcomp> at 0x7f5ef6665df0, file \"snake.py\", line 15>:\\n 15           0 BUILD_LIST               0\\n              2 LOAD_FAST                0 (.0)\\n        >>    4 FOR_ITER                16 (to 22)\\n              6 UNPACK_SEQUENCE          2\\n              8 STORE_FAST               1 (a)\\n             10 STORE_FAST               2 (b)\\n             12 LOAD_FAST                1 (a)\\n             14 LOAD_FAST                2 (b)\\n             16 BINARY_XOR\\n             18 LIST_APPEND              2\\n             20 JUMP_ABSOLUTE            4\\n        >>   22 RETURN_VALUE\\n'"
      ]
     },
     "execution_count": 13,
     "metadata": {},
     "output_type": "execute_result"
    }
   ],
   "source": [
    "with open(\"snake.txt\", \"r\") as f:\n",
    "    text = f.read()\n",
    "\n",
    "text"
   ]
  },
  {
   "cell_type": "code",
   "execution_count": 14,
   "metadata": {},
   "outputs": [
    {
     "data": {
      "text/plain": [
       "[['  1           0 LOAD_CONST               0 (4)',\n",
       "  '              2 LOAD_CONST               1 (54)',\n",
       "  '              4 LOAD_CONST               2 (41)',\n",
       "  '              6 LOAD_CONST               3 (0)',\n",
       "  '              8 LOAD_CONST               4 (112)',\n",
       "  '             10 LOAD_CONST               5 (32)',\n",
       "  '             12 LOAD_CONST               6 (25)',\n",
       "  '             14 LOAD_CONST               7 (49)',\n",
       "  '             16 LOAD_CONST               8 (33)',\n",
       "  '             18 LOAD_CONST               9 (3)',\n",
       "  '             20 LOAD_CONST               3 (0)',\n",
       "  '             22 LOAD_CONST               3 (0)',\n",
       "  '             24 LOAD_CONST              10 (57)',\n",
       "  '             26 LOAD_CONST               5 (32)',\n",
       "  '             28 LOAD_CONST              11 (108)',\n",
       "  '             30 LOAD_CONST              12 (23)',\n",
       "  '             32 LOAD_CONST              13 (48)',\n",
       "  '             34 LOAD_CONST               0 (4)',\n",
       "  '             36 LOAD_CONST              14 (9)',\n",
       "  '             38 LOAD_CONST              15 (70)',\n",
       "  '             40 LOAD_CONST              16 (7)',\n",
       "  '             42 LOAD_CONST              17 (110)',\n",
       "  '             44 LOAD_CONST              18 (36)',\n",
       "  '             46 LOAD_CONST              19 (8)',\n",
       "  '             48 LOAD_CONST              11 (108)',\n",
       "  '             50 LOAD_CONST              16 (7)',\n",
       "  '             52 LOAD_CONST               7 (49)',\n",
       "  '             54 LOAD_CONST              20 (10)',\n",
       "  '             56 LOAD_CONST               0 (4)',\n",
       "  '             58 LOAD_CONST              21 (86)',\n",
       "  '             60 LOAD_CONST              22 (43)',\n",
       "  '             62 LOAD_CONST              11 (108)',\n",
       "  '             64 LOAD_CONST              23 (122)',\n",
       "  '             66 LOAD_CONST              24 (14)',\n",
       "  '             68 LOAD_CONST              25 (2)',\n",
       "  '             70 LOAD_CONST              26 (71)',\n",
       "  '             72 LOAD_CONST              27 (62)',\n",
       "  '             74 LOAD_CONST              28 (115)',\n",
       "  '             76 LOAD_CONST              29 (88)',\n",
       "  '             78 LOAD_CONST              30 (78)',\n",
       "  '             80 BUILD_LIST              40',\n",
       "  '             82 STORE_NAME               0 (input_list)'],\n",
       " [\"  2          84 LOAD_CONST              31 ('J')\",\n",
       "  '             86 STORE_NAME               1 (key_str)'],\n",
       " [\"  3          88 LOAD_CONST              32 ('_')\",\n",
       "  '             90 LOAD_NAME                1 (key_str)',\n",
       "  '             92 BINARY_ADD',\n",
       "  '             94 STORE_NAME               1 (key_str)'],\n",
       " ['  4          96 LOAD_NAME                1 (key_str)',\n",
       "  \"             98 LOAD_CONST              33 ('o')\",\n",
       "  '            100 BINARY_ADD',\n",
       "  '            102 STORE_NAME               1 (key_str)'],\n",
       " ['  5         104 LOAD_NAME                1 (key_str)',\n",
       "  \"            106 LOAD_CONST              34 ('3')\",\n",
       "  '            108 BINARY_ADD',\n",
       "  '            110 STORE_NAME               1 (key_str)'],\n",
       " [\"  6         112 LOAD_CONST              35 ('t')\",\n",
       "  '            114 LOAD_NAME                1 (key_str)',\n",
       "  '            116 BINARY_ADD',\n",
       "  '            118 STORE_NAME               1 (key_str)'],\n",
       " ['  9         120 LOAD_CONST              36 (<code object <listcomp> at 0x7f5ef6665d40, file \"snake.py\", line 9>)',\n",
       "  \"            122 LOAD_CONST              37 ('<listcomp>')\",\n",
       "  '            124 MAKE_FUNCTION            0',\n",
       "  '            126 LOAD_NAME                1 (key_str)',\n",
       "  '            128 GET_ITER',\n",
       "  '            130 CALL_FUNCTION            1',\n",
       "  '            132 STORE_NAME               2 (key_list)'],\n",
       " [' 11     >>  134 LOAD_NAME                3 (len)',\n",
       "  '            136 LOAD_NAME                2 (key_list)',\n",
       "  '            138 CALL_FUNCTION            1',\n",
       "  '            140 LOAD_NAME                3 (len)',\n",
       "  '            142 LOAD_NAME                0 (input_list)',\n",
       "  '            144 CALL_FUNCTION            1',\n",
       "  '            146 COMPARE_OP               0 (<)',\n",
       "  '            148 POP_JUMP_IF_FALSE      162'],\n",
       " [' 12         150 LOAD_NAME                2 (key_list)',\n",
       "  '            152 LOAD_METHOD              4 (extend)',\n",
       "  '            154 LOAD_NAME                2 (key_list)',\n",
       "  '            156 CALL_METHOD              1',\n",
       "  '            158 POP_TOP',\n",
       "  '            160 JUMP_ABSOLUTE          134'],\n",
       " [' 15     >>  162 LOAD_CONST              38 (<code object <listcomp> at 0x7f5ef6665df0, file \"snake.py\", line 15>)',\n",
       "  \"            164 LOAD_CONST              37 ('<listcomp>')\",\n",
       "  '            166 MAKE_FUNCTION            0',\n",
       "  '            168 LOAD_NAME                5 (zip)',\n",
       "  '            170 LOAD_NAME                0 (input_list)',\n",
       "  '            172 LOAD_NAME                2 (key_list)',\n",
       "  '            174 CALL_FUNCTION            2',\n",
       "  '            176 GET_ITER',\n",
       "  '            178 CALL_FUNCTION            1',\n",
       "  '            180 STORE_NAME               6 (result)'],\n",
       " [\" 18         182 LOAD_CONST              39 ('')\",\n",
       "  '            184 LOAD_METHOD              7 (join)',\n",
       "  '            186 LOAD_NAME                8 (map)',\n",
       "  '            188 LOAD_NAME                9 (chr)',\n",
       "  '            190 LOAD_NAME                6 (result)',\n",
       "  '            192 CALL_FUNCTION            2',\n",
       "  '            194 CALL_METHOD              1',\n",
       "  '            196 STORE_NAME              10 (result_text)',\n",
       "  '            198 LOAD_CONST              40 (None)',\n",
       "  '            200 RETURN_VALUE'],\n",
       " ['Disassembly of <code object <listcomp> at 0x7f5ef6665d40, file \"snake.py\", line 9>:',\n",
       "  '  9           0 BUILD_LIST               0',\n",
       "  '              2 LOAD_FAST                0 (.0)',\n",
       "  '        >>    4 FOR_ITER                12 (to 18)',\n",
       "  '              6 STORE_FAST               1 (char)',\n",
       "  '              8 LOAD_GLOBAL              0 (ord)',\n",
       "  '             10 LOAD_FAST                1 (char)',\n",
       "  '             12 CALL_FUNCTION            1',\n",
       "  '             14 LIST_APPEND              2',\n",
       "  '             16 JUMP_ABSOLUTE            4',\n",
       "  '        >>   18 RETURN_VALUE'],\n",
       " ['Disassembly of <code object <listcomp> at 0x7f5ef6665df0, file \"snake.py\", line 15>:',\n",
       "  ' 15           0 BUILD_LIST               0',\n",
       "  '              2 LOAD_FAST                0 (.0)',\n",
       "  '        >>    4 FOR_ITER                16 (to 22)',\n",
       "  '              6 UNPACK_SEQUENCE          2',\n",
       "  '              8 STORE_FAST               1 (a)',\n",
       "  '             10 STORE_FAST               2 (b)',\n",
       "  '             12 LOAD_FAST                1 (a)',\n",
       "  '             14 LOAD_FAST                2 (b)',\n",
       "  '             16 BINARY_XOR',\n",
       "  '             18 LIST_APPEND              2',\n",
       "  '             20 JUMP_ABSOLUTE            4',\n",
       "  '        >>   22 RETURN_VALUE']]"
      ]
     },
     "execution_count": 14,
     "metadata": {},
     "output_type": "execute_result"
    }
   ],
   "source": [
    "blocks = text.split(\"\\n\\n\")\n",
    "blocks = [b.splitlines() for b in blocks]\n",
    "blocks"
   ]
  },
  {
   "cell_type": "code",
   "execution_count": 15,
   "metadata": {},
   "outputs": [
    {
     "data": {
      "text/plain": [
       "[TITLE: 1\n",
       " -----------\n",
       " 0 LOAD_CONST 0 (4)\n",
       "               2 LOAD_CONST               1 (54)\n",
       "               4 LOAD_CONST               2 (41)\n",
       "               6 LOAD_CONST               3 (0)\n",
       "               8 LOAD_CONST               4 (112)\n",
       "              10 LOAD_CONST               5 (32)\n",
       "              12 LOAD_CONST               6 (25)\n",
       "              14 LOAD_CONST               7 (49)\n",
       "              16 LOAD_CONST               8 (33)\n",
       "              18 LOAD_CONST               9 (3)\n",
       "              20 LOAD_CONST               3 (0)\n",
       "              22 LOAD_CONST               3 (0)\n",
       "              24 LOAD_CONST              10 (57)\n",
       "              26 LOAD_CONST               5 (32)\n",
       "              28 LOAD_CONST              11 (108)\n",
       "              30 LOAD_CONST              12 (23)\n",
       "              32 LOAD_CONST              13 (48)\n",
       "              34 LOAD_CONST               0 (4)\n",
       "              36 LOAD_CONST              14 (9)\n",
       "              38 LOAD_CONST              15 (70)\n",
       "              40 LOAD_CONST              16 (7)\n",
       "              42 LOAD_CONST              17 (110)\n",
       "              44 LOAD_CONST              18 (36)\n",
       "              46 LOAD_CONST              19 (8)\n",
       "              48 LOAD_CONST              11 (108)\n",
       "              50 LOAD_CONST              16 (7)\n",
       "              52 LOAD_CONST               7 (49)\n",
       "              54 LOAD_CONST              20 (10)\n",
       "              56 LOAD_CONST               0 (4)\n",
       "              58 LOAD_CONST              21 (86)\n",
       "              60 LOAD_CONST              22 (43)\n",
       "              62 LOAD_CONST              11 (108)\n",
       "              64 LOAD_CONST              23 (122)\n",
       "              66 LOAD_CONST              24 (14)\n",
       "              68 LOAD_CONST              25 (2)\n",
       "              70 LOAD_CONST              26 (71)\n",
       "              72 LOAD_CONST              27 (62)\n",
       "              74 LOAD_CONST              28 (115)\n",
       "              76 LOAD_CONST              29 (88)\n",
       "              78 LOAD_CONST              30 (78)\n",
       "              80 BUILD_LIST              40\n",
       "              82 STORE_NAME               0 (input_list),\n",
       " TITLE: 2\n",
       " -----------\n",
       " 84 LOAD_CONST 31 ('J')\n",
       "              86 STORE_NAME               1 (key_str),\n",
       " TITLE: 3\n",
       " -----------\n",
       " 88 LOAD_CONST 32 ('_')\n",
       "              90 LOAD_NAME                1 (key_str)\n",
       "              92 BINARY_ADD\n",
       "              94 STORE_NAME               1 (key_str),\n",
       " TITLE: 4\n",
       " -----------\n",
       " 96 LOAD_NAME 1 (key_str)\n",
       "              98 LOAD_CONST              33 ('o')\n",
       "             100 BINARY_ADD\n",
       "             102 STORE_NAME               1 (key_str),\n",
       " TITLE: 5\n",
       " -----------\n",
       " 104 LOAD_NAME 1 (key_str)\n",
       "             106 LOAD_CONST              34 ('3')\n",
       "             108 BINARY_ADD\n",
       "             110 STORE_NAME               1 (key_str),\n",
       " TITLE: 6\n",
       " -----------\n",
       " 112 LOAD_CONST 35 ('t')\n",
       "             114 LOAD_NAME                1 (key_str)\n",
       "             116 BINARY_ADD\n",
       "             118 STORE_NAME               1 (key_str),\n",
       " TITLE: 9\n",
       " -----------\n",
       " 120 LOAD_CONST 36 (<code object <listcomp> at 0x7f5ef6665d40, file \"snake.py\", line 9>)\n",
       "             122 LOAD_CONST              37 ('<listcomp>')\n",
       "             124 MAKE_FUNCTION            0\n",
       "             126 LOAD_NAME                1 (key_str)\n",
       "             128 GET_ITER\n",
       "             130 CALL_FUNCTION            1\n",
       "             132 STORE_NAME               2 (key_list),\n",
       " TITLE: 11\n",
       " -----------\n",
       " >> 134 LOAD_NAME 3 (len)\n",
       "             136 LOAD_NAME                2 (key_list)\n",
       "             138 CALL_FUNCTION            1\n",
       "             140 LOAD_NAME                3 (len)\n",
       "             142 LOAD_NAME                0 (input_list)\n",
       "             144 CALL_FUNCTION            1\n",
       "             146 COMPARE_OP               0 (<)\n",
       "             148 POP_JUMP_IF_FALSE      162,\n",
       " TITLE: 12\n",
       " -----------\n",
       " 150 LOAD_NAME 2 (key_list)\n",
       "             152 LOAD_METHOD              4 (extend)\n",
       "             154 LOAD_NAME                2 (key_list)\n",
       "             156 CALL_METHOD              1\n",
       "             158 POP_TOP\n",
       "             160 JUMP_ABSOLUTE          134,\n",
       " TITLE: 15\n",
       " -----------\n",
       " >> 162 LOAD_CONST 38 (<code object <listcomp> at 0x7f5ef6665df0, file \"snake.py\", line 15>)\n",
       "             164 LOAD_CONST              37 ('<listcomp>')\n",
       "             166 MAKE_FUNCTION            0\n",
       "             168 LOAD_NAME                5 (zip)\n",
       "             170 LOAD_NAME                0 (input_list)\n",
       "             172 LOAD_NAME                2 (key_list)\n",
       "             174 CALL_FUNCTION            2\n",
       "             176 GET_ITER\n",
       "             178 CALL_FUNCTION            1\n",
       "             180 STORE_NAME               6 (result),\n",
       " TITLE: 18\n",
       " -----------\n",
       " 182 LOAD_CONST 39 ('')\n",
       "             184 LOAD_METHOD              7 (join)\n",
       "             186 LOAD_NAME                8 (map)\n",
       "             188 LOAD_NAME                9 (chr)\n",
       "             190 LOAD_NAME                6 (result)\n",
       "             192 CALL_FUNCTION            2\n",
       "             194 CALL_METHOD              1\n",
       "             196 STORE_NAME              10 (result_text)\n",
       "             198 LOAD_CONST              40 (None)\n",
       "             200 RETURN_VALUE,\n",
       " TITLE: Disassembly of <code object <listcomp> at 0x7f5ef6665d40, file \"snake.py\", line 9>:\n",
       " -----------\n",
       "   9           0 BUILD_LIST               0\n",
       "               2 LOAD_FAST                0 (.0)\n",
       "         >>    4 FOR_ITER                12 (to 18)\n",
       "               6 STORE_FAST               1 (char)\n",
       "               8 LOAD_GLOBAL              0 (ord)\n",
       "              10 LOAD_FAST                1 (char)\n",
       "              12 CALL_FUNCTION            1\n",
       "              14 LIST_APPEND              2\n",
       "              16 JUMP_ABSOLUTE            4\n",
       "         >>   18 RETURN_VALUE,\n",
       " TITLE: Disassembly of <code object <listcomp> at 0x7f5ef6665df0, file \"snake.py\", line 15>:\n",
       " -----------\n",
       "  15           0 BUILD_LIST               0\n",
       "               2 LOAD_FAST                0 (.0)\n",
       "         >>    4 FOR_ITER                16 (to 22)\n",
       "               6 UNPACK_SEQUENCE          2\n",
       "               8 STORE_FAST               1 (a)\n",
       "              10 STORE_FAST               2 (b)\n",
       "              12 LOAD_FAST                1 (a)\n",
       "              14 LOAD_FAST                2 (b)\n",
       "              16 BINARY_XOR\n",
       "              18 LIST_APPEND              2\n",
       "              20 JUMP_ABSOLUTE            4\n",
       "         >>   22 RETURN_VALUE]"
      ]
     },
     "execution_count": 15,
     "metadata": {},
     "output_type": "execute_result"
    }
   ],
   "source": [
    "class Bb:\n",
    "    def __init__(self, lines: list[str]) -> None:\n",
    "        if lines[0].startswith(\"Disassembly\"):\n",
    "            self.title = lines[0]\n",
    "            self.lines = lines[1:]\n",
    "        else:\n",
    "            (index, *rest) = lines[0].split()\n",
    "            self.title = index\n",
    "            self.lines = [\" \".join(rest)] + lines[1:]\n",
    "\n",
    "    def __repr__(self) -> str:\n",
    "        lines = '\\n'.join(self.lines)\n",
    "        return f\"TITLE: {self.title}\\n-----------\\n{lines}\\n\"\n",
    "\n",
    "blocks = [Bb(b) for b in blocks]\n",
    "\n",
    "blocks"
   ]
  },
  {
   "cell_type": "code",
   "execution_count": null,
   "metadata": {},
   "outputs": [],
   "source": []
  }
 ],
 "metadata": {
  "kernelspec": {
   "display_name": "Python 3",
   "language": "python",
   "name": "python3"
  },
  "language_info": {
   "codemirror_mode": {
    "name": "ipython",
    "version": 3
   },
   "file_extension": ".py",
   "mimetype": "text/x-python",
   "name": "python",
   "nbconvert_exporter": "python",
   "pygments_lexer": "ipython3",
   "version": "3.11.9"
  }
 },
 "nbformat": 4,
 "nbformat_minor": 2
}
